mcp_arduino_server/__init__.py
mcp_arduino_server/server.py
mcp_arduino_server-0.1.5.dist-info/licenses/LICENSE
mcp_arduino_server-0.1.5.dist-info/METADATA
mcp_arduino_server-0.1.5.dist-info/WHEEL
mcp_arduino_server-0.1.5.dist-info/entry_points.txt
mcp_arduino_server-0.1.5.dist-info/top_level.txt
mcp_arduino_server-0.1.5.dist-info/RECORD
