Metadata-Version: 2.4
Name: mcp-arduino-server
Version: 0.1.5
Summary: MCP Server for Arduino CLI providing sketch, board, library, and file management tools.
Author-email: Volt23 <ernesto.volt@me.com>
Project-URL: Homepage, https://github.com/Volt23/mcp-arduino-server
Project-URL: Repository, https://github.com/Volt23/mcp-arduino-server
Keywords: mcp,model context protocol,arduino,arduino-cli,llm,ai
Classifier: Development Status :: 3 - Alpha
Classifier: Programming Language :: Python :: 3
Classifier: Programming Language :: Python :: 3.8
Classifier: Programming Language :: Python :: 3.9
Classifier: Programming Language :: Python :: 3.10
Classifier: Programming Language :: Python :: 3.11
Classifier: Programming Language :: Python :: 3.12
Classifier: License :: OSI Approved :: MIT License
Classifier: Operating System :: OS Independent
Classifier: Intended Audience :: Developers
Classifier: Topic :: Software Development :: Embedded Systems
Classifier: Topic :: Scientific/Engineering :: Artificial Intelligence
Requires-Python: >=3.10
License-File: LICENSE
Requires-Dist: mcp[cli]
Requires-Dist: thefuzz[speedup]>=0.20.0
Requires-Dist: wireviz
Requires-Dist: openai
Dynamic: license-file
